hks_pylib/__init__.py
hks_pylib/done.py
hks_pylib/hksenum.py
hks_pylib/http.py
hks_pylib/math.py
hks_pylib/utils.py
hks_pylib/version.py
hks_pylib/cryptography/__init__.py
hks_pylib/cryptography/hashes.py
hks_pylib/cryptography/protocols.py
hks_pylib/cryptography/batchcrypt/__init__.py
hks_pylib/cryptography/batchcrypt/batchnumber.py
hks_pylib/cryptography/batchcrypt/integer.py
hks_pylib/cryptography/batchcrypt/quantization.py
hks_pylib/cryptography/ciphers/__init__.py
hks_pylib/cryptography/ciphers/asymmetrics.py
hks_pylib/cryptography/ciphers/cipherid.py
hks_pylib/cryptography/ciphers/hkscipher.py
hks_pylib/cryptography/ciphers/keygenerator.py
hks_pylib/cryptography/ciphers/symmetrics.py
hks_pylib/errors/__init__.py
hks_pylib/errors/done.py
hks_pylib/errors/files.py
hks_pylib/errors/hksenum.py
hks_pylib/errors/http.py
hks_pylib/errors/logger.py
hks_pylib/errors/math.py
hks_pylib/errors/cryptography/__init__.py
hks_pylib/errors/cryptography/batchcrypt/__init__.py
hks_pylib/errors/cryptography/batchcrypt/batchnumber.py
hks_pylib/errors/cryptography/batchcrypt/integer.py
hks_pylib/errors/cryptography/batchcrypt/quantization.py
hks_pylib/errors/cryptography/ciphers/__init__.py
hks_pylib/errors/cryptography/ciphers/asymmetrics.py
hks_pylib/errors/cryptography/ciphers/cipherid.py
hks_pylib/errors/cryptography/ciphers/symmetrics.py
hks_pylib/files/__init__.py
hks_pylib/files/generator.py
hks_pylib/logger/__init__.py
hks_pylib/logger/config.py
hks_pylib/logger/logger.py
hks_pylib/logger/logger_generator.py
hks_pylib/logger/standard.py
hks_pylib-0.0.8.dist-info/LICENSE
hks_pylib-0.0.8.dist-info/METADATA
hks_pylib-0.0.8.dist-info/WHEEL
hks_pylib-0.0.8.dist-info/top_level.txt
hks_pylib-0.0.8.dist-info/RECORD
