Metadata-Version: 2.1
Name: hks-pylib
Version: 0.0.8
Summary: A python utility library is written by huykingsofm
Home-page: https://github.com/huykingsofm/hks_pylib
Author: huykingsofm
Author-email: huykingsofm@gmail.com
License: UNKNOWN
Project-URL: Bug Tracker, https://github.com/huykingsofm/hks_pylib/issues
Platform: UNKNOWN
Classifier: Programming Language :: Python :: 3
Classifier: License :: OSI Approved :: MIT License
Classifier: Operating System :: OS Independent
Requires-Python: >=3.7.1
Requires-Dist: cryptography (==3.4.7)
Requires-Dist: hkserror (==0.0.2)
